APS_BlueSky_tools/__init__.py
APS_BlueSky_tools/_version.py
APS_BlueSky_tools/callbacks.py
APS_BlueSky_tools/devices.py
APS_BlueSky_tools/examples.py
APS_BlueSky_tools/filewriters.py
APS_BlueSky_tools/legacy_code___devices.py
APS_BlueSky_tools/plans.py
APS_BlueSky_tools/signals.py
APS_BlueSky_tools/snapshot.py
APS_BlueSky_tools/suspenders.py
APS_BlueSky_tools/utils.py
APS_BlueSky_tools/synApps_ophyd/__init__.py
APS_BlueSky_tools/synApps_ophyd/busy.py
APS_BlueSky_tools/synApps_ophyd/sscan.py
APS_BlueSky_tools/synApps_ophyd/swait.py
APS_BlueSky_tools-2019.103.0.dist-info/METADATA
APS_BlueSky_tools-2019.103.0.dist-info/RECORD
APS_BlueSky_tools-2019.103.0.dist-info/WHEEL
APS_BlueSky_tools-2019.103.0.dist-info/entry_points.txt
APS_BlueSky_tools-2019.103.0.dist-info/top_level.txt
